permualgebra/__init__.py
permualgebra/cycle.py
permualgebra/permutation.py
permualgebra-0.0.1.dist-info/LICENSE
permualgebra-0.0.1.dist-info/METADATA
permualgebra-0.0.1.dist-info/WHEEL
permualgebra-0.0.1.dist-info/top_level.txt
permualgebra-0.0.1.dist-info/RECORD
