Metadata-Version: 2.1
Name: permualgebra
Version: 0.0.1
Summary: Calculate the permutations with Python.
Home-page: https://github.com/EYH0602/permualgbra
Author: Yifeng He
Author-email: yfhe@ucdavis.edu
License: UNKNOWN
Platform: UNKNOWN
Classifier: Programming Language :: Python :: 3
Classifier: License :: OSI Approved :: GNU General Public License v3 (GPLv3)
Classifier: Operating System :: OS Independent
Requires-Python: >=3.6
